<?xml version="1.0" encoding="UTF-8" ?>
<odoo>
    <record id="view_pinakes_product_tag_form" model="ir.ui.view">
        <field name="name">pinakes.product.public.category.form</field>
        <field name="model">product.public.category</field>
        <field name="inherit_id" ref="website_sale.product_public_category_form_view"/>
        <field name="arch" type="xml">
            <field name="parent_id" position="after">
                <field name="tag_ids" widget="many2many_tags" options="{'color_field': 'color'}"/>
            </field>
        </field>
    </record>
</odoo>
